{
  "grid_w": 0,
  "grid_h": 0,
  "depth": 16,
  "preset": "cat6x4",
  "label": "Caterpillar C(6,4)",
  "edges": [
    [0, 1],
    [1, 2],
    [2, 3],
    [3, 4],
    [4, 5],
    [0, 6],
    [0, 7],
    [0, 8],
    [0, 9],
    [1, 10],
    [1, 11],
    [1, 12],
    [1, 13],
    [2, 14],
    [2, 15],
    [2, 16],
    [2, 17],
    [3, 18],
    [3, 19],
    [3, 20],
    [3, 21],
    [4, 22],
    [4, 23],
    [4, 24],
    [4, 25],
    [5, 26],
    [5, 27],
    [5, 28],
    [5, 29]
  ],
  "states": [
    { "b": 0, "e": 536870911, "move": -1, "actor": "Init" },
    { "b": 16, "e": 536870911, "move": 4, "actor": "Burner" },
    { "b": 16, "e": 536870903, "move": 3, "actor": "Builder" },
    { "b": 48, "e": 536870903, "move": 5, "actor": "Burner" },
    { "b": 48, "e": 536870887, "move": 4, "actor": "Builder" },
    { "b": 4194352, "e": 536870887, "move": 22, "actor": "Burner" },
    { "b": 4194352, "e": 532676583, "move": 22, "actor": "Builder" },
    { "b": 20971568, "e": 532676583, "move": 24, "actor": "Burner" },
    { "b": 20971568, "e": 515899367, "move": 24, "actor": "Builder" },
    { "b": 88080432, "e": 515899367, "move": 26, "actor": "Burner" },
    { "b": 88080432, "e": 448790503, "move": 26, "actor": "Builder" },
    { "b": 356515888, "e": 448790503, "move": 28, "actor": "Burner" },
    { "b": 356515888, "e": 180355047, "move": 28, "actor": "Builder" },
    { "b": 356515888, "e": 178257895, "move": 21, "actor": "Builder" },
    { "b": 356515888, "e": 169869287, "move": 23, "actor": "Builder" }
  ],
  "nash_value": 6,
  "nodes_searched": 2649740866,
  "time_ms": 169066
}
